MANIFEST.in
README.rst
setup.cfg
setup.py
Products/__init__.py
Products.BrFieldsAndWidgets.egg-info/PKG-INFO
Products.BrFieldsAndWidgets.egg-info/SOURCES.txt
Products.BrFieldsAndWidgets.egg-info/dependency_links.txt
Products.BrFieldsAndWidgets.egg-info/entry_points.txt
Products.BrFieldsAndWidgets.egg-info/namespace_packages.txt
Products.BrFieldsAndWidgets.egg-info/not-zip-safe
Products.BrFieldsAndWidgets.egg-info/requires.txt
Products.BrFieldsAndWidgets.egg-info/top_level.txt
Products/BrFieldsAndWidgets/BrFieldsAndWidgets.py
Products/BrFieldsAndWidgets/README.txt
Products/BrFieldsAndWidgets/__init__.py
Products/BrFieldsAndWidgets/config.py
Products/BrFieldsAndWidgets/configure.zcml
Products/BrFieldsAndWidgets/interfaces.py
Products/BrFieldsAndWidgets/testing.py
Products/BrFieldsAndWidgets/validators.py
Products/BrFieldsAndWidgets/version.txt
Products/BrFieldsAndWidgets/Extensions/Install.py
Products/BrFieldsAndWidgets/content/BrFieldsAndWidgets.py
Products/BrFieldsAndWidgets/content/BrFieldsAndWidgetsDemo.py
Products/BrFieldsAndWidgets/content/__init__.py
Products/BrFieldsAndWidgets/content/at_mixin.py
Products/BrFieldsAndWidgets/content/br_endereco.py
Products/BrFieldsAndWidgets/locales/Products.BrFieldsAndWidgets.pot
Products/BrFieldsAndWidgets/locales/manual.pot
Products/BrFieldsAndWidgets/locales/rebuildAll.sh
Products/BrFieldsAndWidgets/locales/pt_BR/LC_MESSAGES/Products.BrFieldsAndWidgets.mo
Products/BrFieldsAndWidgets/locales/pt_BR/LC_MESSAGES/Products.BrFieldsAndWidgets.po
Products/BrFieldsAndWidgets/profiles/default/metadata.xml
Products/BrFieldsAndWidgets/profiles/default/skins.xml
Products/BrFieldsAndWidgets/profiles/example/factorytool.xml
Products/BrFieldsAndWidgets/profiles/example/metadata.xml
Products/BrFieldsAndWidgets/profiles/example/types.xml
Products/BrFieldsAndWidgets/profiles/example/types/BrFieldsAndWidgetsDemo.xml
Products/BrFieldsAndWidgets/profiles/uninstall/skins.xml
Products/BrFieldsAndWidgets/skins/BrF_images/BrPhone.gif
Products/BrFieldsAndWidgets/skins/BrF_images/CEP.gif
Products/BrFieldsAndWidgets/skins/BrF_images/CNPJ.gif
Products/BrFieldsAndWidgets/skins/BrF_images/CPF.gif
Products/BrFieldsAndWidgets/skins/BrF_templates/BrCEP.pt
Products/BrFieldsAndWidgets/skins/BrF_templates/BrCNPJ.pt
Products/BrFieldsAndWidgets/skins/BrF_templates/BrCPF.pt
Products/BrFieldsAndWidgets/skins/BrF_templates/BrFieldsAndWidgets.js
