Metadata-Version: 1.0
Name: Products.BrFieldsAndWidgets
Version: 1.2.2
Summary: Brazilian fields and widgets to be used with Plone and Archetypes
Home-page: https://github.com/collective/Products.BrFieldsAndWidgets
Author: Simples Consultoria
Author-email: products@simplesconsultoria.com.br
License: GPL
Keywords: plone archetypes widget BrFieldsAndWidgets brazil brasil
Platform: UNKNOWN
Classifier: Framework :: Plone
Classifier: Framework :: Plone :: 3.3
Classifier: Framework :: Plone :: 4.0
Classifier: Framework :: Plone :: 4.1
Classifier: Framework :: Zope2
Classifier: Framework :: Zope3
Classifier: Intended Audience :: Developers
Classifier: Natural Language :: Portuguese (Brazilian)
Classifier: Programming Language :: Python
Classifier: Topic :: Software Development :: Libraries :: Python Modules
